setup.py
src/me2/__init__.py
src/me2/packaging/__init__.py
src/me2/packaging/app.py
src/me2/packaging/dric.py
src/me2/packaging/package.py
src/me2/packaging/tools.py
src/me2_packager.egg-info/PKG-INFO
src/me2_packager.egg-info/SOURCES.txt
src/me2_packager.egg-info/dependency_links.txt
src/me2_packager.egg-info/entry_points.txt
src/me2_packager.egg-info/namespace_packages.txt
src/me2_packager.egg-info/requires.txt
src/me2_packager.egg-info/top_level.txt