Metadata-Version: 1.1
Name: me2-packager
Version: 0.0.2
Summary: me2-pack is the packaging component of me2
Home-page: http://developers.mosaic-cloud.eu
Author: Marian Neagul
Author-email: marian@ieat.ro
License: APL
Keywords: packaging mOSAIC
Platform: UNKNOWN
Classifier: Intended Audience :: System Administrators
Classifier: Development Status :: 3 - Alpha
Classifier: Topic :: System :: Archiving :: Packaging
Classifier: License :: OSI Approved :: Apache Software License
